asgi_amqp/__init__.py
asgi_amqp/core.py
asgi_amqp/models.py
asgi_amqp/migrations/0001_initial.py
asgi_amqp/migrations/__init__.py
asgi_amqp/tests/__init__.py
asgi_amqp-1.1.4.dist-info/LICENSE
asgi_amqp-1.1.4.dist-info/METADATA
asgi_amqp-1.1.4.dist-info/WHEEL
asgi_amqp-1.1.4.dist-info/top_level.txt
asgi_amqp-1.1.4.dist-info/RECORD
