Metadata-Version: 2.1
Name: asgi-amqp
Version: 1.1.4
Summary: AMQP-backed ASGI channel layer implementation
Home-page: http://github.com/ansible/asgi_amqp/
Author: Wayne Witzel III
Author-email: wayne@riotousliving.com
License: BSD
Keywords: asgi_amqp asgi amqp rabbitmq django channels
Platform: UNKNOWN
Classifier: Development Status :: 5 - Production/Stable
Classifier: Environment :: Web Environment
Classifier: Intended Audience :: Developers
Classifier: Intended Audience :: System Administrators
Classifier: License :: OSI Approved :: BSD License
Classifier: Operating System :: MacOS :: MacOS X
Classifier: Operating System :: Microsoft :: Windows
Classifier: Operating System :: POSIX
Classifier: Programming Language :: Python
Classifier: Programming Language :: Python :: 2.7
Classifier: Programming Language :: Python :: 3.6
Requires-Dist: six
Requires-Dist: kombu (>=3.0.35)
Requires-Dist: msgpack-python (>=0.4.7)
Requires-Dist: asgiref (==1.1.2)
Requires-Dist: jsonpickle (>=0.9.3)
